mutation_bench/__init__.py
mutation_bench/muthrp.py
mutation_bench/perl_scripts/annotate_variation.pl
mutation_bench/perl_scripts/convert2annovar.pl
mutation_bench-5.8.dist-info/METADATA
mutation_bench-5.8.dist-info/WHEEL
mutation_bench-5.8.dist-info/entry_points.txt
mutation_bench-5.8.dist-info/top_level.txt
mutation_bench-5.8.dist-info/RECORD
