Metadata-Version: 2.1
Name: mutation-bench
Version: 5.8
Summary: A tool for Prediction of high-risk cancer patients using mutation profiles
Home-page: https://github.com/raghavagps/mutation_bench
Requires-Python: >=3.8
Requires-Dist: numpy
Requires-Dist: pandas (==1.4.0)
Requires-Dist: rpy2
Requires-Dist: xgboost
Requires-Dist: ranger
Requires-Dist: scikit-learn
Requires-Dist: tqdm
